LICENSE.rst
MANIFEST.in
README.rst
setup.py
acl/__init__.py
acl/exceptions.py
acl/netscreen.py
acl/parser.py
acl/rcs.py
acl/tools.py
acl.egg-info/PKG-INFO
acl.egg-info/SOURCES.txt
acl.egg-info/dependency_links.txt
acl.egg-info/requires.txt
acl.egg-info/top_level.txt
docs/Makefile
docs/acl.rst
docs/acl_script.rst
docs/aclconv.rst
docs/check_access.rst
docs/conf.py
docs/examples.rst
docs/index.rst
docs/license.rst
docs/make.bat